CHANGES.txt
Makefile
README.rst
README.txt
bootstrap.py
buildout.cfg
setup.py
docs/LICENSE.GPL
docs/LICENSE.txt
docs/screenshot.png
local/CHANGES.txt
local/Makefile
local/README.txt
local/bootstrap.py
local/buildout.cfg
local/setup.py
local/docs/LICENSE.GPL
local/docs/LICENSE.txt
local/docs/screenshot.png
local/src/cosent/__init__.py
local/src/cosent/guruscan/__init__.py
local/src/cosent/guruscan/config.py
local/src/cosent/guruscan/configure.zcml
local/src/cosent/guruscan/controlpanel.py
local/src/cosent/guruscan/i18n.py
local/src/cosent/guruscan/interfaces.py
local/src/cosent/guruscan/testing.py
local/src/cosent/guruscan/Extensions/Install.py
local/src/cosent/guruscan/Extensions/__init__.py
local/src/cosent/guruscan/browser/__init__.py
local/src/cosent/guruscan/browser/configure.zcml
local/src/cosent/guruscan/browser/exportusers.pt
local/src/cosent/guruscan/browser/exportusers.py
local/src/cosent/guruscan/browser/guruscan.pt
local/src/cosent/guruscan/browser/guruscan.py
local/src/cosent/guruscan/profiles/default/actions.xml
local/src/cosent/guruscan/profiles/default/browserlayer.xml
local/src/cosent/guruscan/profiles/default/controlpanel.xml
local/src/cosent/guruscan/profiles/default/metadata.xml
local/src/cosent/guruscan/profiles/default/registry.xml
local/src/cosent/guruscan/profiles/uninstall/actions.xml
local/src/cosent/guruscan/profiles/uninstall/registry.xml
local/src/cosent/guruscan/tests/__init__.py
local/src/cosent/guruscan/tests/test_controlpanel.py
local/src/cosent/guruscan/tests/test_setup.py
parts/omelette/cosent/guruscan/__init__.py
parts/omelette/cosent/guruscan/config.py
parts/omelette/cosent/guruscan/configure.zcml
parts/omelette/cosent/guruscan/controlpanel.py
parts/omelette/cosent/guruscan/i18n.py
parts/omelette/cosent/guruscan/interfaces.py
parts/omelette/cosent/guruscan/testing.py
parts/omelette/cosent/guruscan/Extensions/Install.py
parts/omelette/cosent/guruscan/Extensions/__init__.py
parts/omelette/cosent/guruscan/browser/__init__.py
src/cosent.guruscan.egg-info/PKG-INFO
src/cosent.guruscan.egg-info/SOURCES.txt
src/cosent.guruscan.egg-info/dependency_links.txt
src/cosent.guruscan.egg-info/entry_points.txt
src/cosent.guruscan.egg-info/namespace_packages.txt
src/cosent.guruscan.egg-info/not-zip-safe
src/cosent.guruscan.egg-info/requires.txt
src/cosent.guruscan.egg-info/top_level.txt
