Metadata-Version: 1.1
Name: cosent.guruscan
Version: 1.0dev
Summary: Plone integration for GuruScan
Home-page: http://github.com/cosent/cosent.guruscan
Author: Guido Stevens
Author-email: guido.stevens@cosent.net
License: gpl
Keywords: zope,plone,guruscan
Platform: UNKNOWN
Classifier: Programming Language :: Python
